datastore_dnnevo_client/__init__.py
datastore_dnnevo_client/client.py
datastore_dnnevo_client-0.1.2.dist-info/LICENSE
datastore_dnnevo_client-0.1.2.dist-info/METADATA
datastore_dnnevo_client-0.1.2.dist-info/WHEEL
datastore_dnnevo_client-0.1.2.dist-info/top_level.txt
datastore_dnnevo_client-0.1.2.dist-info/RECORD
