Metadata-Version: 2.1
Name: datastore-dnnevo-client
Version: 0.1.2
Summary: Client for datastore
Home-page: UNKNOWN
Author: mereszeta
Author-email: grzegorzszeremeta@gmail.com
License: UNKNOWN
Platform: UNKNOWN
Classifier: Programming Language :: Python :: 3
Classifier: License :: OSI Approved :: MIT License
Classifier: Operating System :: OS Independent
Requires-Python: >=3.6
Requires-Dist: requests
